sunrise6g_opensdk/__init__.py
sunrise6g_opensdk/logger.py
sunrise6g_opensdk/common/__init__.py
sunrise6g_opensdk/common/adapters_factory.py
sunrise6g_opensdk/common/sdk.py
sunrise6g_opensdk/edgecloud/__init__.py
sunrise6g_opensdk/edgecloud/adapters/__init__.py
sunrise6g_opensdk/edgecloud/adapters/errors.py
sunrise6g_opensdk/edgecloud/adapters/aeros/__init__.py
sunrise6g_opensdk/edgecloud/adapters/aeros/client.py
sunrise6g_opensdk/edgecloud/adapters/aeros/config.py
sunrise6g_opensdk/edgecloud/adapters/aeros/continuum_client.py
sunrise6g_opensdk/edgecloud/adapters/aeros/utils.py
sunrise6g_opensdk/edgecloud/adapters/i2edge/__init__.py
sunrise6g_opensdk/edgecloud/adapters/i2edge/client.py
sunrise6g_opensdk/edgecloud/adapters/i2edge/common.py
sunrise6g_opensdk/edgecloud/adapters/i2edge/gsma_utils.py
sunrise6g_opensdk/edgecloud/adapters/i2edge/schemas.py
sunrise6g_opensdk/edgecloud/adapters/i2edge/utils.py
sunrise6g_opensdk/edgecloud/adapters/kubernetes/__init__.py
sunrise6g_opensdk/edgecloud/adapters/kubernetes/client.py
sunrise6g_opensdk/edgecloud/adapters/kubernetes/lib/type_util.py
sunrise6g_opensdk/edgecloud/adapters/kubernetes/lib/util.py
sunrise6g_opensdk/edgecloud/adapters/kubernetes/lib/core/__init__.py
sunrise6g_opensdk/edgecloud/adapters/kubernetes/lib/core/piedge_encoder.py
sunrise6g_opensdk/edgecloud/adapters/kubernetes/lib/models/__init__.py
sunrise6g_opensdk/edgecloud/adapters/kubernetes/lib/models/activate_secured_slice.py
sunrise6g_opensdk/edgecloud/adapters/kubernetes/lib/models/app_delete.py
sunrise6g_opensdk/edgecloud/adapters/kubernetes/lib/models/app_manifest.py
sunrise6g_opensdk/edgecloud/adapters/kubernetes/lib/models/app_manifest_app_repo.py
sunrise6g_opensdk/edgecloud/adapters/kubernetes/lib/models/app_manifest_component_spec.py
sunrise6g_opensdk/edgecloud/adapters/kubernetes/lib/models/app_manifest_network_interfaces.py
sunrise6g_opensdk/edgecloud/adapters/kubernetes/lib/models/appdeploy.py
sunrise6g_opensdk-2.0.0.dist-info/licenses/LICENSE
sunrise6g_opensdk-2.0.0.dist-info/METADATA
sunrise6g_opensdk-2.0.0.dist-info/WHEEL
sunrise6g_opensdk-2.0.0.dist-info/top_level.txt
sunrise6g_opensdk-2.0.0.dist-info/RECORD
