Metadata-Version: 2.4
Name: sunrise6g-opensdk
Version: 2.0.0
Summary: ⚠️ Deprecated — This SDK has moved to https://labs.etsi.org/rep/oop/code/tf-sdk/-/packages/
Author-email: Adrian Pino <adrian.pino@i2cat.net>
License: Apache-2.0
Project-URL: Homepage, https://sunrise6g.eu/
Project-URL: Repository, https://github.com/OpenOperatorPlatform/OpenSDK
Keywords: Federation,Transformation Functions,TFs,CAMARA,GSMA OPG,Open source,OpenSDK,SDK,SUNRISE-6G,6G,ETSI,Edge Cloud Platform,5G Core,Open RAN,O-RAN
Classifier: Development Status :: 7 - Inactive
Classifier: License :: OSI Approved :: Apache Software License
Classifier: Programming Language :: Python :: 3
Requires-Python: >=3.7
License-File: LICENSE
Requires-Dist: auto_mix_prep==0.2.0
Requires-Dist: colorlog==6.8.2
Requires-Dist: pydantic==2.11.3
Requires-Dist: pydantic-extra-types==2.10.3
Requires-Dist: requests==2.32.4
Requires-Dist: pymongo==4.13.2
Requires-Dist: kubernetes==33.1.0
Dynamic: license-file
